vanillaplusjs/constants.py
vanillaplusjs/http_server.py
vanillaplusjs/main.py
vanillaplusjs/build/build_context.py
vanillaplusjs/build/build_file.py
vanillaplusjs/build/build_file_result.py
vanillaplusjs/build/cold_incremental_rebuild.py
vanillaplusjs/build/exceptions.py
vanillaplusjs/build/file_signature.py
vanillaplusjs/build/graph.py
vanillaplusjs/build/hot_incremental_rebuild.py
vanillaplusjs/build/ioutil.py
vanillaplusjs/build/scan_file.py
vanillaplusjs/build/scan_file_result.py
vanillaplusjs/build/css/builder.py
vanillaplusjs/build/css/manipulate_and_serialize.py
vanillaplusjs/build/css/manipulator.py
vanillaplusjs/build/css/serializer.py
vanillaplusjs/build/css/token.py
vanillaplusjs/build/css/tokenizer.py
vanillaplusjs/build/css/manips/nest.py
vanillaplusjs/build/css/manips/outline_image_data.py
vanillaplusjs/build/css/manips/version_urls.py
vanillaplusjs/build/css/manips/icons/color.py
vanillaplusjs/build/css/manips/icons/command.py
vanillaplusjs/build/css/manips/icons/manip.py
vanillaplusjs/build/css/manips/icons/parser.py
vanillaplusjs/build/css/manips/icons/settings.py
vanillaplusjs/build/css/manips/icons/token.py
vanillaplusjs/build/css/manips/icons/tokenizer.py
vanillaplusjs/build/handlers/copy.py
vanillaplusjs/build/handlers/copy_and_hash.py
vanillaplusjs/build/handlers/css.py
vanillaplusjs/build/handlers/handler.py
vanillaplusjs/build/handlers/hash.py
vanillaplusjs/build/handlers/html.py
vanillaplusjs/build/handlers/image_glue.py
vanillaplusjs/build/handlers/js.py
vanillaplusjs/build/handlers/js_constants.py
vanillaplusjs/build/html/builder.py
vanillaplusjs/build/html/manipulate_and_serialize.py
vanillaplusjs/build/html/manipulator.py
vanillaplusjs/build/html/token.py
vanillaplusjs/build/html/tokenizer.py
vanillaplusjs/build/html/manips/link_hash.py
vanillaplusjs/build/html/manips/link_rel_canonical.py
vanillaplusjs/build/html/manips/link_rel_stylesheet_hash.py
vanillaplusjs/build/html/manips/outline.py
vanillaplusjs/build/html/manips/template.py
vanillaplusjs-1.3.2.dist-info/LICENSE
vanillaplusjs-1.3.2.dist-info/METADATA
vanillaplusjs-1.3.2.dist-info/WHEEL
vanillaplusjs-1.3.2.dist-info/entry_points.txt
vanillaplusjs-1.3.2.dist-info/top_level.txt
vanillaplusjs-1.3.2.dist-info/RECORD
