Metadata-Version: 2.1
Name: vanillaplusjs
Version: 1.3.2
Summary: A lightweight html/css/js framework
Home-page: https://github.com/tjstretchalot/vanillaplusjs
Author: Timothy Moore
Author-email: mtimothy984@gmail.com
Classifier: Programming Language :: Python :: 3
Classifier: Programming Language :: Python :: 3.8
Classifier: Programming Language :: Python :: 3.9
Classifier: Programming Language :: Python :: 3.10
Classifier: License :: OSI Approved :: MIT License
Classifier: Topic :: Internet :: WWW/HTTP
Classifier: Topic :: Software Development :: Pre-processors
Classifier: Intended Audience :: Developers
License-File: LICENSE
Requires-Dist: pillow
Requires-Dist: pytypeutils
Requires-Dist: requests
Requires-Dist: loguru
Requires-Dist: html5lib
Requires-Dist: watchdog
Requires-Dist: fasteners
Requires-Dist: starlette
Requires-Dist: uvicorn
